lenskit_tf/__init__.py
lenskit_tf/_pt.py
lenskit_tf/biasedmf.py
lenskit_tf/bpr.py
lenskit_tf/ibmf.py
lenskit_tf/util.py
lenskit_tf-0.14.0.dist-info/LICENSE.md
lenskit_tf-0.14.0.dist-info/WHEEL
lenskit_tf-0.14.0.dist-info/METADATA
lenskit_tf-0.14.0.dist-info/RECORD
